[{"__type__":"cc.SpriteFrame","content":{"name":"tanchuang_03","texture":"1c6bd698f","rect":[3,94,95,86],"offset":[0,0],"originalSize":[95,86],"capInsets":[34,33,34,31]}},{"__type__":"cc.SpriteFrame","content":{"name":"singleColor","texture":"1c6bd698f","rect":[95,50,2,2],"offset":[0,0],"originalSize":[2,2],"capInsets":[0,0,0,0]}},[{"__type__":"cc.Prefab","_name":"BoxSeeAdTip","data":{"__id__":1}},{"__type__":"cc.Node","_name":"BoxSeeAdTip","_children":[{"__id__":2},{"__id__":3}],"_level":1,"_components":[{"__type__":"08341uqK4JLu4NgrEAkcNk4","node":{"__id__":1},"content":{"__id__":3}},{"__type__":"cee215jx1xJNL7HDOLg95bx","node":{"__id__":1},"boxTopSprite":{"__id__":12},"boxBottomSprite":{"__id__":10}},{"__type__":"cc.Widget","node":{"__id__":1},"_alignFlags":45}],"_prefab":{"__type__":"cc.PrefabInfo","root":{"__id__":1},"asset":{"__uuid__":"639zzUHLJJdL1Gw3KUC6Sh"},"fileId":"afYlnYORBEor+wVRBxznUi"},"_contentSize":{"__type__":"cc.Size","width":720,"height":1280},"_position":{"__type__":"cc.Vec3","x":360,"y":640}},{"__type__":"cc.Node","_name":"blackMask","_parent":{"__id__":1},"_level":2,"_components":[{"__type__":"cc.Sprite","node":{"__id__":2},"_spriteFrame":{"__uuid__":"41D7kWhyFGY7q4NDlzkazn"},"_sizeMode":0},{"__type__":"cc.Widget","node":{"__id__":2},"_alignFlags":45,"_originalWidth":360,"_originalHeight":640},{"__type__":"cc.BlockInputEvents","node":{"__id__":2}}],"_prefab":{"__type__":"cc.PrefabInfo","root":{"__id__":1},"asset":{"__uuid__":"639zzUHLJJdL1Gw3KUC6Sh"},"fileId":"2fdy6omAhGeZbgh3O1rUDD"},"_opacity":102,"_color":{"__type__":"cc.Color"},"_contentSize":{"__type__":"cc.Size","width":360,"height":640},"_scale":{"__type__":"cc.Vec3","x":2,"y":2,"z":1}},{"__type__":"cc.Node","_name":"content","_parent":{"__id__":1},"_children":[{"__id__":4},{"__id__":5},{"__id__":8},{"__id__":13},{"__id__":14}],"_level":2,"_prefab":{"__type__":"cc.PrefabInfo","root":{"__id__":1},"asset":{"__uuid__":"639zzUHLJJdL1Gw3KUC6Sh"},"fileId":"5c6G5eLHNIgIu6c7oGie0W"}},{"__type__":"cc.Node","_name":"New Node","_parent":{"__id__":3},"_level":3,"_components":[{"__type__":"cc.Sprite","node":{"__id__":4},"_spriteFrame":{"__uuid__":"1cWN7Dyi1AqI56zZLjaE+Q"},"_type":1,"_sizeMode":0}],"_prefab":{"__type__":"cc.PrefabInfo","root":{"__id__":1},"asset":{"__uuid__":"639zzUHLJJdL1Gw3KUC6Sh"},"fileId":"c1MHmvav9CaogRb9B753L4"},"_contentSize":{"__type__":"cc.Size","width":450,"height":450}},{"__type__":"cc.Node","_name":"anniu_fanglv","_parent":{"__id__":3},"_children":[{"__id__":6},{"__id__":7}],"_level":3,"_components":[{"__type__":"cc.Sprite","node":{"__id__":5},"_spriteFrame":{"__uuid__":"a1irboFxJD/4EUeMRzauac"},"_type":1,"_sizeMode":0},{"__type__":"cc.Button","node":{"__id__":5},"clickEvents":[{"__type__":"cc.ClickEvent","target":{"__id__":1},"_componentId":"cee215jx1xJNL7HDOLg95bx","handler":"onSeeAd"}],"_N$transition":3,"transition":3},{"__type__":"25145voH4lPb5myYNaNSRAq","node":{"__id__":5}}],"_prefab":{"__type__":"cc.PrefabInfo","root":{"__id__":1},"asset":{"__uuid__":"639zzUHLJJdL1Gw3KUC6Sh"},"fileId":"01YeuxaqZE/7Kob2HlDA/F"},"_contentSize":{"__type__":"cc.Size","width":280,"height":109},"_position":{"__type__":"cc.Vec3","y":-216}},{"__type__":"cc.Node","_name":"New Sprite","_parent":{"__id__":5},"_level":4,"_components":[{"__type__":"cc.Sprite","node":{"__id__":6},"_spriteFrame":{"__uuid__":"d0utcR2P1KCYYisVY+EruJ"}}],"_prefab":{"__type__":"cc.PrefabInfo","root":{"__id__":1},"asset":{"__uuid__":"639zzUHLJJdL1Gw3KUC6Sh"},"fileId":"6e6BOrKB5BgawXARHusALh"},"_contentSize":{"__type__":"cc.Size","width":55,"height":58},"_position":{"__type__":"cc.Vec3","x":125,"y":52},"_rotationX":15,"_rotationY":15,"_quat":{"__type__":"cc.Quat","z":-0.13052619222005157,"w":0.9914448613738104}},{"__type__":"cc.Node","_name":"New Label","_parent":{"__id__":5},"_level":4,"_components":[{"__type__":"cc.Label","node":{"__id__":7},"_useOriginalSize":false,"_string":"好的呀","_N$string":"好的呀","_fontSize":45,"_lineHeight":60,"_N$horizontalAlign":1,"_N$verticalAlign":1},{"__type__":"cc.LabelOutline","node":{"__id__":7},"_color":{"__type__":"cc.Color","r":70,"g":69,"b":69},"_width":2},{"__type__":"11b50mf2i9Ky4vZtb6crC39","node":{"__id__":7},"_stringId":"BOX.WATCH_VIDEO.BTN_YES","_N$string":"BOX.WATCH_VIDEO.BTN_YES"}],"_prefab":{"__type__":"cc.PrefabInfo","root":{"__id__":1},"asset":{"__uuid__":"639zzUHLJJdL1Gw3KUC6Sh"},"fileId":"e7UyDjpMZOMavah7ZmvL+T"},"_contentSize":{"__type__":"cc.Size","width":139,"height":60}},{"__type__":"cc.Node","_name":"New Node","_parent":{"__id__":3},"_children":[{"__id__":9},{"__id__":11}],"_level":3,"_prefab":{"__type__":"cc.PrefabInfo","root":{"__id__":1},"asset":{"__uuid__":"639zzUHLJJdL1Gw3KUC6Sh"},"fileId":"d5gfIEMMpJxqOLFJy4ODvq"},"_position":{"__type__":"cc.Vec3","y":14}},{"__type__":"cc.Node","_name":"New Sprite","_parent":{"__id__":8},"_level":3,"_components":[{"__id__":10}],"_prefab":{"__type__":"cc.PrefabInfo","root":{"__id__":1},"asset":{"__uuid__":"639zzUHLJJdL1Gw3KUC6Sh"},"fileId":"9f8rx8yaFB4oMkC2LZhy6u"},"_contentSize":{"__type__":"cc.Size","width":177,"height":79}},{"__type__":"cc.Sprite","node":{"__id__":9}},{"__type__":"cc.Node","_name":"New Sprite","_parent":{"__id__":8},"_level":3,"_components":[{"__id__":12}],"_prefab":{"__type__":"cc.PrefabInfo","root":{"__id__":1},"asset":{"__uuid__":"639zzUHLJJdL1Gw3KUC6Sh"},"fileId":"82QAj0NG1OvocpjztBFM3y"},"_contentSize":{"__type__":"cc.Size","width":189,"height":113},"_position":{"__type__":"cc.Vec3","y":50}},{"__type__":"cc.Sprite","node":{"__id__":11}},{"__type__":"cc.Node","_name":"New Label","_parent":{"__id__":3},"_level":3,"_components":[{"__type__":"cc.Label","node":{"__id__":13},"_useOriginalSize":false,"_string":"是否观看广告使用\n第二个宝箱开启栏？","_N$string":"是否观看广告使用\n第二个宝箱开启栏？","_fontSize":30,"_N$horizontalAlign":1,"_N$verticalAlign":1,"_N$overflow":3},{"__type__":"11b50mf2i9Ky4vZtb6crC39","node":{"__id__":13},"_stringId":"BOX.WATCH_VIDEO.INFO","_N$string":"BOX.WATCH_VIDEO.INFO"}],"_prefab":{"__type__":"cc.PrefabInfo","root":{"__id__":1},"asset":{"__uuid__":"639zzUHLJJdL1Gw3KUC6Sh"},"fileId":"7etepvwUFH0Ydttf/+lyfC"},"_color":{"__type__":"cc.Color","r":49,"g":49,"b":49},"_contentSize":{"__type__":"cc.Size","width":270,"height":80},"_position":{"__type__":"cc.Vec3","y":-83}},{"__type__":"cc.Node","_name":"New Label","_parent":{"__id__":3},"_level":3,"_components":[{"__type__":"cc.Label","node":{"__id__":14},"_useOriginalSize":false,"_string":"不了，谢谢","_N$string":"不了，谢谢","_fontSize":35,"_N$horizontalAlign":1,"_N$verticalAlign":1},{"__type__":"cc.Button","node":{"__id__":14},"clickEvents":[{"__type__":"cc.ClickEvent","target":{"__id__":1},"_componentId":"08341uqK4JLu4NgrEAkcNk4","handler":"close"},{"__type__":"cc.ClickEvent","target":{"__id__":1},"_componentId":"cee215jx1xJNL7HDOLg95bx","handler":"onClose"}],"_N$transition":3,"transition":3},{"__type__":"11b50mf2i9Ky4vZtb6crC39","node":{"__id__":14},"_stringId":"BOX.WATCH_VIDEO.BTN_NO","_N$string":"BOX.WATCH_VIDEO.BTN_NO"}],"_prefab":{"__type__":"cc.PrefabInfo","root":{"__id__":1},"asset":{"__uuid__":"639zzUHLJJdL1Gw3KUC6Sh"},"fileId":"0fWOs03qxPo7oM763LRiqS"},"_contentSize":{"__type__":"cc.Size","width":175,"height":40},"_position":{"__type__":"cc.Vec3","y":-296}}],{"__type__":"cc.SpriteFrame","content":{"name":"anniu_fanglv","texture":"1c6bd698f","rect":[306,3,95,78],"offset":[0,0],"originalSize":[95,78],"capInsets":[30,25,30,21]}},{"__type__":"cc.SpriteFrame","content":{"name":"videoIcon","texture":"1c6bd698f","rect":[306,87,55,58],"offset":[0,0],"originalSize":[55,58],"capInsets":[0,0,0,0]}}]